test_run_dir/SingleCycle.Launcher1554891941/ALU.v
`ifdef RANDOMIZE_GARBAGE_ASSIGN
`define RANDOMIZE
`endif
`ifdef RANDOMIZE_INVALID_ASSIGN
`define RANDOMIZE
`endif
`ifdef RANDOMIZE_REG_INIT
`define RANDOMIZE
`endif
`ifdef RANDOMIZE_MEM_INIT
`define RANDOMIZE
`endif

module ALU(
  input         clock,
  input         reset,
  input  [31:0] io_a,
  input  [31:0] io_b,
  input  [3:0]  io_op,
  input  [4:0]  io_shamt,
  output [31:0] io_out,
  output        io_zero
);
  wire  _T_9;
  wire [31:0] _T_10;
  wire  _T_12;
  wire [31:0] _T_13;
  wire  _T_15;
  wire [31:0] _T_17;
  wire  _T_19;
  wire [31:0] _T_20;
  wire  _T_22;
  wire [32:0] _T_23;
  wire [31:0] _T_24;
  wire  _T_26;
  wire [32:0] _T_27;
  wire [32:0] _T_28;
  wire [31:0] _T_29;
  wire  _T_31;
  wire [62:0] _GEN_10;
  wire [62:0] _T_32;
  wire  _T_34;
  wire [31:0] _T_35;
  wire  _T_37;
  wire  _T_38;
  wire  _T_40;
  wire [62:0] _T_42;
  wire [62:0] _GEN_0;
  wire [62:0] _GEN_1;
  wire [62:0] _GEN_2;
  wire [62:0] _GEN_3;
  wire [62:0] _GEN_4;
  wire [62:0] _GEN_5;
  wire [62:0] _GEN_6;
  wire [62:0] _GEN_7;
  wire [62:0] _GEN_8;
  wire [62:0] _GEN_9;
  wire  _T_48;
  assign _T_9 = io_op == 4'h0;
  assign _T_10 = io_a & io_b;
  assign _T_12 = io_op == 4'h1;
  assign _T_13 = io_a | io_b;
  assign _T_15 = io_op == 4'h2;
  assign _T_17 = ~ _T_13;
  assign _T_19 = io_op == 4'h3;
  assign _T_20 = io_a ^ io_b;
  assign _T_22 = io_op == 4'h4;
  assign _T_23 = io_a + io_b;
  assign _T_24 = _T_23[31:0];
  assign _T_26 = io_op == 4'h5;
  assign _T_27 = io_a - io_b;
  assign _T_28 = $unsigned(_T_27);
  assign _T_29 = _T_28[31:0];
  assign _T_31 = io_op == 4'h6;
  assign _GEN_10 = {{31'd0}, io_b};
  assign _T_32 = _GEN_10 << io_shamt;
  assign _T_34 = io_op == 4'h7;
  assign _T_35 = io_b >> io_shamt;
  assign _T_37 = io_op == 4'h8;
  assign _T_38 = io_a < io_b;
  assign _T_40 = io_op == 4'h9;
  assign _T_42 = _GEN_10 << 5'h10;
  assign _GEN_0 = _T_40 ? _T_42 : 63'h0;
  assign _GEN_1 = _T_37 ? {{62'd0}, _T_38} : _GEN_0;
  assign _GEN_2 = _T_34 ? {{31'd0}, _T_35} : _GEN_1;
  assign _GEN_3 = _T_31 ? _T_32 : _GEN_2;
  assign _GEN_4 = _T_26 ? {{31'd0}, _T_29} : _GEN_3;
  assign _GEN_5 = _T_22 ? {{31'd0}, _T_24} : _GEN_4;
  assign _GEN_6 = _T_19 ? {{31'd0}, _T_20} : _GEN_5;
  assign _GEN_7 = _T_15 ? {{31'd0}, _T_17} : _GEN_6;
  assign _GEN_8 = _T_12 ? {{31'd0}, _T_13} : _GEN_7;
  assign _GEN_9 = _T_9 ? {{31'd0}, _T_10} : _GEN_8;
  assign _T_48 = _T_29 == 32'h0;
  assign io_out = _GEN_9[31:0];
  assign io_zero = _T_48;
endmodule

test_run_dir/SingleCycle.Launcher1554891941/ALU.vcd
$version Generated by VerilatedVcd $end
$date Fri Jun 15 17:13:39 2018
 $end
$timescale   1ns $end

 $scope module TOP $end
  $var wire  1 # clock $end
  $var wire 32 % io_a [31:0] $end
  $var wire 32 & io_b [31:0] $end
  $var wire  4 ' io_op [3:0] $end
  $var wire 32 ) io_out [31:0] $end
  $var wire  5 ( io_shamt [4:0] $end
  $var wire  1 * io_zero $end
  $var wire  1 $ reset $end
  $scope module ALU $end
   $var wire  1 # clock $end
   $var wire 32 % io_a [31:0] $end
   $var wire 32 & io_b [31:0] $end
   $var wire  4 ' io_op [3:0] $end
   $var wire 32 ) io_out [31:0] $end
   $var wire  5 ( io_shamt [4:0] $end
   $var wire  1 * io_zero $end
   $var wire  1 $ reset $end
  $upscope $end
 $upscope $end
$enddefinitions $end


#0
0#
1$
b00000000000000000000000000000000 %
b00000000000000000000000000000000 &
b0000 '
b00000 (
b00000000000000000000000000000000 )
1*
#1
1#
#2
0#
#3
1#
#4
0#
#5
1#
#6
0#
#7
1#
#8
0#
#9
1#
#10
0#
0$
b00000000000000000000001011101101 %
b00000000000000000000101001011100 &
b0110 '
b01011 (
b00000000010100101110000000000000 )
0*
#11
1#
#12
0#
b00000000000000000000100000100011 %
b00000000000000000000001110000001 &
b0101 '
b10111 (
b00000000000000000000010010100010 )
#13
1#
#14
0#
b00000000000000000000101100001011 %
b00000000000000000000010001100010 &
b0010 '
b00100 (
b11111111111111111111000010010100 )
#15
1#
#16
0#
b00000000000000000000100010010110 %
b00000000000000000000010000111100 &
b0101 '
b10010 (
b00000000000000000000010001011010 )
#17
1#
#18
0#
b00000000000000000000000110110001 %
b00000000000000000000000100000001 &
b1001 '
b10110 (
b00000001000000010000000000000000 )
#19
1#
#20
0#
b00000000000000000000100110101011 %
b00000000000000000000010010101101 &
b1000 '
b11000 (
b00000000000000000000000000000000 )
#21
1#
#22
0#
b00000000000000000000011101010100 %
b00000000000000000000100111100111 &
b10101 (
b00000000000000000000000000000001 )
#23
1#
#24
0#
b00000000000000000000011110100001 %
b00000000000000000000000000110110 &
b0100 '
b00100 (
b00000000000000000000011111010111 )
#25
1#
#26
0#
b00000000000000000000010110101101 %
b00000000000000000000011000111101 &
b0000 '
b11110 (
b00000000000000000000010000101101 )
#27
1#
#28
0#
b00000000000000000000100101111001 %
b00000000000000000000100110110101 &
b0111 '
b10010 (
b00000000000000000000000000000000 )
#29
1#
#30
0#
b00000000000000000000011111110011 %
b00000000000000000000110010000101 &
b0010 '
b01010 (
b11111111111111111111000000001000 )
#31
1#
#32
0#
b00000000000000000000101100010100 %
b00000000000000000000101110000000 &
b0011 '
b10110 (
b00000000000000000000000010010100 )
#33
1#
#34
0#
b00000000000000000000101000000011 %
b00000000000000000000010000111100 &
b0110 '
b11101 (
b10000000000000000000000000000000 )
#35
1#
#36
0#
b00000000000000000000001011111000 %
b00000000000000000000101111101010 &
b1001 '
b10101 (
b00001011111010100000000000000000 )
#37
1#
#38
0#
b00000000000000000000011111111011 %
b00000000000000000000010111010111 &
b0111 '
b01010 (
b00000000000000000000000000000001 )
#39
1#
#40
0#
b00000000000000000000000110101011 %
b00000000000000000000101010111110 &
b1001 '
b01101 (
b00001010101111100000000000000000 )
#41
1#
#42
0#
b00000000000000000000001011011010 %
b00000000000000000000010010100111 &
b0001 '
b10100 (
b00000000000000000000011011111111 )
#43
1#
#44
0#
b00000000000000000000001101110101 %
b00000000000000000000000000000000 &
b0000 '
b01111 (
b00000000000000000000000000000000 )
#45
1#
#46
0#
b00000000000000000000110001100010 %
b00000000000000000000011101010111 &
b0101 '
b00101 (
b00000000000000000000010100001011 )
#47
1#
#48
0#
b00000000000000000000101011100010 %
b00000000000000000000000100110001 &
b0010 '
b01111 (
b11111111111111111111010000001100 )
#49
1#
#50
0#
b00000000000000000000010010010110 %
b00000000000000000000010001001010 &
b0101 '
b00101 (
b00000000000000000000000001001100 )
#51
1#
#52
0#
b00000000000000000000001001111110 %
b00000000000000000000010100101001 &
b1001 '
b01101 (
b00000101001010010000000000000000 )
#53
1#
#54
0#
b00000000000000000000100000011011 %
b00000000000000000000100010111111 &
b0110 '
b11010 (
b11111100000000000000000000000000 )
#55
1#
#56
0#
b00000000000000000000101101110110 %
b00000000000000000000001001111101 &
b0011 '
b00111 (
b00000000000000000000100100001011 )
#57
1#
#58
0#
b00000000000000000000100101111010 %
b00000000000000000000101100101111 &
b0001 '
b00010 (
b00000000000000000000101101111111 )
#59
1#
#60
0#
b00000000000000000000001010011101 %
b00000000000000000000010100111000 &
b1000 '
b10110 (
b00000000000000000000000000000001 )
#61
1#
#62
0#
b00000000000000000000000011011100 %
b00000000000000000000110001001011 &
b0100 '
b11001 (
b00000000000000000000110100100111 )
#63
1#
#64
0#
b00000000000000000000001011100100 %
b00000000000000000000001110100011 &
b0111 '
b11101 (
b00000000000000000000000000000000 )
#65
1#
#66
0#
b00000000000000000000110000101100 %
b00000000000000000000001001100000 &
b10101 (
#67
1#
#68
0#
b00000000000000000000001010111111 %
b00000000000000000000001101011110 &
b0101 '
b11011 (
b11111111111111111111111101100001 )
#69
1#
#70
0#
b00000000000000000000101010011001 %
b00000000000000000000011011110100 &
b0011 '
b01011 (
b00000000000000000000110001101101 )
#71
1#
#72
0#
b00000000000000000000001110000111 %
b00000000000000000000101110100110 &
b0001 '
b11010 (
b00000000000000000000101110100111 )
#73
1#
#74
0#
b00000000000000000000010100010000 %
b00000000000000000000001100101000 &
b01011 (
b00000000000000000000011100111000 )
#75
1#
#76
0#
b00000000000000000000001001010010 %
b00000000000000000000101110101111 &
b0110 '
b01111 (
b00000101110101111000000000000000 )
#77
1#
#78
0#
b00000000000000000000001111000101 %
b00000000000000000000001101110101 &
b10100 (
b00110111010100000000000000000000 )
#79
1#
#80
0#
b00000000000000000000101100111101 %
b00000000000000000000110010001001 &
b0101 '
b10000 (
b11111111111111111111111010110100 )
#81
1#
#82
0#
b00000000000000000000101111101011 %
b00000000000000000000101000010001 &
b0110 '
b11101 (
b00100000000000000000000000000000 )
#83
1#
#84
0#
b00000000000000000000011011000010 %
b00000000000000000000101100111101 &
b0100 '
b00001 (
b00000000000000000001000111111111 )
#85
1#
#86
0#
b00000000000000000000000101010111 %
b00000000000000000000100000101001 &
b0111 '
b10101 (
b00000000000000000000000000000000 )
#87
1#
#88
0#
b00000000000000000000100000100001 %
b00000000000000000000010010101111 &
b0110 '
b01100 (
b00000000010010101111000000000000 )
